fdlite/__init__.py
fdlite/errors.py
fdlite/exif.py
fdlite/face_detection.py
fdlite/face_landmark.py
fdlite/iris_landmark.py
fdlite/nms.py
fdlite/render.py
fdlite/transform.py
fdlite/types.py
fdlite/data/camdb.csv
fdlite/data/camdb.txt
fdlite/data/face_detection_back.tflite
fdlite/data/face_detection_front.tflite
fdlite/data/face_detection_full_range.tflite
fdlite/data/face_detection_full_range_sparse.tflite
fdlite/data/face_detection_short_range.tflite
fdlite/data/face_landmark.tflite
fdlite/data/iris_landmark.tflite
fdlite/examples/__init__.py
fdlite/examples/iris_recoloring.py
face_detection_tflite-0.6.0.dist-info/LICENSE
face_detection_tflite-0.6.0.dist-info/METADATA
face_detection_tflite-0.6.0.dist-info/WHEEL
face_detection_tflite-0.6.0.dist-info/top_level.txt
face_detection_tflite-0.6.0.dist-info/RECORD
