Metadata-Version: 2.1
Name: face-detection-tflite
Version: 0.6.0
Summary: A Python port of Google MediaPipe Face Detection modules
Home-page: https://github.com/patlevin/face-detection-tflite
Author: Patrick Levin
Author-email: vertical-pink@protonmail.com
License: MIT
Project-URL: Bug Tracker, https://github.com/patlevin/face-detection-tflite/issues
Keywords: AI,face-detection,tensorflow,tflite,face-landmarks,iris-detection,face-mesh
Platform: UNKNOWN
Classifier: Programming Language :: Python :: 3
Classifier: License :: OSI Approved :: MIT License
Classifier: Operating System :: OS Independent
Classifier: Development Status :: 4 - Beta
Classifier: Intended Audience :: Developers
Classifier: Topic :: Multimedia :: Graphics
Classifier: Topic :: Scientific/Engineering :: Artificial Intelligence
Classifier: Topic :: Scientific/Engineering :: Image Recognition
Classifier: Topic :: Software Development :: Libraries :: Python Modules
Requires-Python: >=3.8
License-File: LICENSE
